icecube_tools/__init__.py
icecube_tools/_version.py
icecube_tools/cosmology.py
icecube_tools/detection_probability.py
icecube_tools/neutrino_calculator.py
icecube_tools/simulator.py
icecube_tools/detector/__init__.py
icecube_tools/detector/angular_resolution.py
icecube_tools/detector/detector.py
icecube_tools/detector/effective_area.py
icecube_tools/detector/energy_resolution.py
icecube_tools/detector/reco_energy_sampler.py
icecube_tools/point_source_likelihood/__init__.py
icecube_tools/point_source_likelihood/energy_likelihood.py
icecube_tools/point_source_likelihood/point_source_likelihood.py
icecube_tools/point_source_likelihood/prior.py
icecube_tools/point_source_likelihood/spatial_likelihood.py
icecube_tools/source/__init__.py
icecube_tools/source/flux_model.py
icecube_tools/source/power_law.py
icecube_tools/source/source_model.py
icecube_tools/utils/__init__.py
icecube_tools/utils/data.py
icecube_tools/utils/vMF.py
tests/__init__.py
tests/conftest.py
tests/test_angular_resolution.py
tests/test_data_interface.py
tests/test_simulation.py
tests/test_source_interface.py
tests/test_supported_datasets.py
icecube_tools-0.2.1.dist-info/METADATA
icecube_tools-0.2.1.dist-info/WHEEL
icecube_tools-0.2.1.dist-info/top_level.txt
icecube_tools-0.2.1.dist-info/RECORD
