Metadata-Version: 2.1
Name: icecube-tools
Version: 0.2.1
Summary: Python tools
Home-page: https://github.com/cescalara/icecube_tools
Author: Francesca Capel
Author-email: capel.francesca@gmail.com
License: UNKNOWN
Project-URL: Bug Tracker, https://github.com/cescalara/icecube_tools/issues
Project-URL: Source Code, https://github.com/cescalara/icecube_tools
Platform: UNKNOWN
Requires-Dist: numpy
Requires-Dist: scipy
Requires-Dist: matplotlib
Requires-Dist: astropy
Requires-Dist: iminuit (<2)
Requires-Dist: jupytext
Requires-Dist: requests-cache
Requires-Dist: requests
Requires-Dist: bs4
Requires-Dist: tqdm
Requires-Dist: versioneer
Requires-Dist: vMF
Requires-Dist: pandas
Requires-Dist: h5py
